[
  {
    "id_Producto": 1,
    "name_Producto": "Hamburguesa de pollo",
    "price_Producto": 8700,
    "image_Producto": "Hamburguesa_1.png"
  },
  {
    "id_Producto": 2,
    "name_Producto": "Hamburguesa Ranchera",
    "price_Producto": 9500,
    "image_Producto": "Hamburguesa_2.png"
  },
  {
    "id_Producto": 3,
    "name_Producto": "Hamburguesa de Queso",
    "price_Producto": 10700,
    "image_Producto": "Hamburguesa_3.png"
  },
  {
    "id_Producto": 4,
    "name_Producto": "Hamburguesa de Carnes",
    "price_Producto": 11800,
    "image_Producto": "Hamburguesa_1.png"
  },
  {
    "id_Producto": 5,
    "name_Producto": "Hamburguesa de Cacauate",
    "price_Producto": 12900,
    "image_Producto": "Hamburguesa_3.png"
  },
  {
    "id_Producto": 6,
    "name_Producto": "Hamburguesa de Aguacate",
    "price_Producto": 12300,
    "image_Producto": "Hamburguesa_6.png"
  },
  {
    "id_Producto": 7,
    "name_Producto": "Hamburguesa de Criolla",
    "price_Producto": 15500,
    "image_Producto": "Hamburguesa_1.png"
  },
  {
    "id_Producto": 7,
    "name_Producto": "Hamburguesa de la Casa",
    "price_Producto": 16200,
    "image_Producto": "Hamburguesa_2.png"
  }
]
